abstract_parallels/__init__.py
abstract_parallels/apis/__init__.py
abstract_parallels/apis/api_gui.py
abstract_parallels/clipit/__init__.py
abstract_parallels/clipit/get_clipit.py
abstract_parallels/services_mgr/__init__.py
abstract_parallels/services_mgr/servicesManager.py
abstract_parallels/window_mgr/__init__.py
abstract_parallels/window_mgr/get_window_mgr.py
abstract_paralells-0.0.0.1.dist-info/METADATA
abstract_paralells-0.0.0.1.dist-info/WHEEL
abstract_paralells-0.0.0.1.dist-info/top_level.txt
abstract_paralells-0.0.0.1.dist-info/RECORD
